requests_unixsocket/__init__.py
requests_unixsocket/adapters.py
requests_unixsocket/testutils.py
requests_unixsocket/tests/test_requests_unixsocket.py
parsys_requests_unixsocket-0.3.2.dist-info/AUTHORS
parsys_requests_unixsocket-0.3.2.dist-info/LICENSE
parsys_requests_unixsocket-0.3.2.dist-info/METADATA
parsys_requests_unixsocket-0.3.2.dist-info/WHEEL
parsys_requests_unixsocket-0.3.2.dist-info/pbr.json
parsys_requests_unixsocket-0.3.2.dist-info/top_level.txt
parsys_requests_unixsocket-0.3.2.dist-info/RECORD
