Metadata-Version: 2.1
Name: parsys-requests-unixsocket
Version: 0.3.2
Summary: Use requests to talk HTTP via a UNIX domain socket
Home-page: https://github.com/parsys-telemedicine/requests-unixsocket
Author: Marc Abramowitz
Author-email: marc@marc-abramowitz.com
License: Apache-2
Classifier: Development Status :: 3 - Alpha
Classifier: Intended Audience :: Developers
Classifier: Intended Audience :: Information Technology
Classifier: License :: OSI Approved :: Apache Software License
Classifier: Operating System :: OS Independent
Classifier: Programming Language :: Python
Classifier: Programming Language :: Python :: 2
Classifier: Programming Language :: Python :: 2.7
Classifier: Programming Language :: Python :: 3
Classifier: Programming Language :: Python :: 3.3
Classifier: Programming Language :: Python :: 3.4
Classifier: Programming Language :: Python :: 3.5
Classifier: Programming Language :: Python :: 3.6
License-File: LICENSE
License-File: AUTHORS
Requires-Dist: requests <3.0,>=2.0
Requires-Dist: urllib3 <3.0,>=2.0
